install/__init__.py
pip_install-1.3.5.dist-info/LICENSE
pip_install-1.3.5.dist-info/METADATA
pip_install-1.3.5.dist-info/WHEEL
pip_install-1.3.5.dist-info/top_level.txt
pip_install-1.3.5.dist-info/RECORD
