Metadata-Version: 2.1
Name: pip-install
Version: 1.3.5
Summary: Install packages from within code
Home-page: https://github.com/eugenekolo/pip-install
Author: Eugene Kolo
Author-email: eugene@kolobyte.com
License: MIT
Keywords: install packages from within code
Platform: UNKNOWN
Classifier: Programming Language :: Python :: 3
Classifier: License :: OSI Approved :: MIT License
Classifier: Operating System :: OS Independent
Requires-Python: >=2.7, >=3.5
